SpiderKo/__init__.py
SpiderKo/__main__.py
SpiderKo/config.py
SpiderKo/monkeys.py
SpiderKo/core/__init__.py
SpiderKo/core/bitmap.py
SpiderKo/core/db.py
SpiderKo/helper/__init__.py
SpiderKo/helper/user_agent.py
SpiderKo/http/__init__.py
SpiderKo/http/async_request.py
SpiderKo/http/sync_request.py
SpiderKo/process/__init__.py
SpiderKo/spider/__init__.py
SpiderKo/spider/upanso.py
SpiderKo/store/__init__.py
SpiderKo/utils/__init__.py
test/__init__.py
test/rakuten/__init__.py
test/rakuten/rakuten.py
SpiderKo-0.0.4.dist-info/METADATA
SpiderKo-0.0.4.dist-info/WHEEL
SpiderKo-0.0.4.dist-info/entry_points.txt
SpiderKo-0.0.4.dist-info/top_level.txt
SpiderKo-0.0.4.dist-info/RECORD
