Metadata-Version: 2.1
Name: SpiderKo
Version: 0.0.4
Summary: Spider Toolkit Collection
Home-page: https://github.com/fovegage/SpiderKo
Author: fovegage
Author-email: fovegage@gmail.com
License: UNKNOWN
Platform: UNKNOWN
Classifier: Programming Language :: Python :: 3
Classifier: License :: OSI Approved :: MIT License
Classifier: Operating System :: OS Independent
Requires-Dist: requests
Requires-Dist: xlrd (==1.2.0)
Requires-Dist: pandas
Requires-Dist: BeautifulSoup4
Requires-Dist: simplepy
Requires-Dist: redis
Requires-Dist: pymongo
